synapse_sdk/__init__.py
synapse_sdk/enums.py
synapse_sdk/exceptions.py
synapse_sdk/loggers.py
synapse_sdk/cli/__init__.py
synapse_sdk/cli/auth.py
synapse_sdk/cli/doctor.py
synapse_sdk/cli/main.py
synapse_sdk/cli/agent/__init__.py
synapse_sdk/cli/agent/config.py
synapse_sdk/cli/agent/select.py
synapse_sdk/cli/plugin/__init__.py
synapse_sdk/cli/plugin/create.py
synapse_sdk/cli/plugin/job.py
synapse_sdk/cli/plugin/publish.py
synapse_sdk/cli/plugin/run.py
synapse_sdk/cli/plugin/test.py
synapse_sdk/clients/README.md
synapse_sdk/clients/__init__.py
synapse_sdk/clients/_template.py
synapse_sdk/clients/base.py
synapse_sdk/clients/exceptions.py
synapse_sdk/clients/protocols.py
synapse_sdk/clients/utils.py
synapse_sdk/clients/validation.py
synapse_sdk/clients/agent/__init__.py
synapse_sdk/clients/agent/async_ray.py
synapse_sdk/clients/agent/container.py
synapse_sdk/clients/agent/plugin.py
synapse_sdk/clients/agent/ray.py
synapse_sdk/clients/backend/__init__.py
synapse_sdk/clients/backend/annotation.py
synapse_sdk/clients/backend/core.py
synapse_sdk/clients/backend/data_collection.py
synapse_sdk/clients/backend/hitl.py
synapse_sdk/clients/backend/integration.py
synapse_sdk/clients/backend/ml.py
synapse_sdk/clients/backend/models.py
synapse_sdk/clients/backend/bulk_upload/__init__.py
synapse_sdk/clients/backend/bulk_upload/base.py
synapse_sdk/clients/backend/bulk_upload/config.py
synapse_sdk/clients/backend/bulk_upload/mixin.py
synapse_sdk/clients/backend/bulk_upload/models.py
synapse_sdk/clients/backend/bulk_upload/registry.py
synapse_sdk/clients/backend/bulk_upload/strategies/__init__.py
synapse_sdk/clients/backend/bulk_upload/strategies/presigned.py
synapse_sdk/clients/pipeline/__init__.py
synapse_sdk/clients/pipeline/client.py
synapse_sdk/integrations/__init__.py
synapse_sdk/integrations/_base.py
synapse_sdk/integrations/_context.py
synapse_sdk/integrations/ultralytics/__init__.py
synapse_sdk/integrations/ultralytics/_callbacks.py
synapse_sdk-2026.1.23.dist-info/licenses/LICENSE
synapse_sdk-2026.1.23.dist-info/METADATA
synapse_sdk-2026.1.23.dist-info/WHEEL
synapse_sdk-2026.1.23.dist-info/entry_points.txt
synapse_sdk-2026.1.23.dist-info/top_level.txt
synapse_sdk-2026.1.23.dist-info/RECORD
