Metadata-Version: 2.4
Name: synapse-sdk
Version: 2026.1.23
Summary: synapse sdk
Author-email: datamaker <developer@datamaker.io>
License:                                  Apache License
Classifier: Programming Language :: Python :: 3
Requires-Python: >=3.12
License-File: LICENSE
Requires-Dist: pydantic>=2.0.0
Requires-Dist: requests>=2.28.0
Requires-Dist: httpx>=0.27.0
Requires-Dist: aiohttp>=3.8.0
Requires-Dist: pyyaml>=6.0.0
Requires-Dist: pyjwt>=2.10.1
Requires-Dist: websocket-client>=1.6.0
Requires-Dist: websockets>=12.0
Requires-Dist: typer>=0.15.0
Requires-Dist: rich>=14.0.0
Requires-Dist: questionary>=2.1.0
Requires-Dist: jinja2>=3.1.0
Requires-Dist: pillow>=10.0.0
Requires-Dist: tqdm>=4.65.0
Provides-Extra: all
Requires-Dist: ray[all]==2.50.0; extra == "all"
Requires-Dist: universal-pathlib>=0.3.7; extra == "all"
Requires-Dist: s3fs>=2024.0.0; extra == "all"
Requires-Dist: gcsfs>=2024.0.0; extra == "all"
Requires-Dist: sshfs>=2024.0.0; extra == "all"
Requires-Dist: mcp>=1.25.0; extra == "all"
Requires-Dist: openpyxl>=3.1.0; extra == "all"
Provides-Extra: test
Requires-Dist: pytest>=7.0.0; extra == "test"
Requires-Dist: pytest-asyncio>=0.21.0; extra == "test"
Requires-Dist: pytest-cov>=4.0.0; extra == "test"
Requires-Dist: pytest-mock>=3.10.0; extra == "test"
Requires-Dist: pytest-timeout>=2.1.0; extra == "test"
Requires-Dist: pytest-xdist>=3.0.0; extra == "test"
Requires-Dist: pytest-html>=3.1.0; extra == "test"
Requires-Dist: pytest-json-report>=1.5.0; extra == "test"
Requires-Dist: requests-mock>=1.10.0; extra == "test"
Requires-Dist: responses>=0.25.0; extra == "test"
Requires-Dist: respx>=0.20.0; extra == "test"
Provides-Extra: dev
Requires-Dist: pre-commit; extra == "dev"
Requires-Dist: ruff>=0.8.0; extra == "dev"
Provides-Extra: docs
Requires-Dist: pydoc-markdown>=4.8.0; extra == "docs"
Dynamic: license-file
